odoo/addons/product_multi_category/README.rst
odoo/addons/product_multi_category/__init__.py
odoo/addons/product_multi_category/__manifest__.py
odoo/addons/product_multi_category/i18n/ca.po
odoo/addons/product_multi_category/i18n/de.po
odoo/addons/product_multi_category/i18n/es.po
odoo/addons/product_multi_category/i18n/fr.po
odoo/addons/product_multi_category/i18n/fr_BE.po
odoo/addons/product_multi_category/i18n/hr.po
odoo/addons/product_multi_category/i18n/it.po
odoo/addons/product_multi_category/i18n/nl_NL.po
odoo/addons/product_multi_category/i18n/product_multi_category.pot
odoo/addons/product_multi_category/i18n/sv.po
odoo/addons/product_multi_category/i18n/tr.po
odoo/addons/product_multi_category/models/__init__.py
odoo/addons/product_multi_category/models/product.py
odoo/addons/product_multi_category/readme/CONTRIBUTORS.rst
odoo/addons/product_multi_category/readme/DESCRIPTION.rst
odoo/addons/product_multi_category/readme/USAGE.rst
odoo/addons/product_multi_category/static/description/icon.png
odoo/addons/product_multi_category/static/description/index.html
odoo/addons/product_multi_category/views/product_view.xml
odoo12_addon_product_multi_category-12.0.1.0.0.99.dev14.dist-info/METADATA
odoo12_addon_product_multi_category-12.0.1.0.0.99.dev14.dist-info/WHEEL
odoo12_addon_product_multi_category-12.0.1.0.0.99.dev14.dist-info/top_level.txt
odoo12_addon_product_multi_category-12.0.1.0.0.99.dev14.dist-info/RECORD
